MANIFEST.in
README.rst
bootstrap.py
buildout.cfg
plone.cfg
setup.cfg
setup.py
docs/HISTORY.txt
docs/INSTALL.txt
docs/LICENSE.GPL
docs/LICENSE.txt
docs/img/folder_contents.png
docs/img/keywordmanager.png
docs/img/tag_import.png
docs/img/tagging_config.png
src/inqbus/__init__.py
src/inqbus.tagging.egg-info/PKG-INFO
src/inqbus.tagging.egg-info/SOURCES.txt
src/inqbus.tagging.egg-info/dependency_links.txt
src/inqbus.tagging.egg-info/entry_points.txt
src/inqbus.tagging.egg-info/namespace_packages.txt
src/inqbus.tagging.egg-info/not-zip-safe
src/inqbus.tagging.egg-info/paster_plugins.txt
src/inqbus.tagging.egg-info/requires.txt
src/inqbus.tagging.egg-info/top_level.txt
src/inqbus/tagging/INTEGRATION.txt
src/inqbus/tagging/__init__.py
src/inqbus/tagging/config.py
src/inqbus/tagging/configure.zcml
src/inqbus/tagging/functions.py
src/inqbus/tagging/interfaces.py
src/inqbus/tagging/testing.py
src/inqbus/tagging/testing.zcml
src/inqbus/tagging/browser/__init__.py
src/inqbus/tagging/browser/actions.py
src/inqbus/tagging/browser/configure.zcml
src/inqbus/tagging/browser/form.py
src/inqbus/tagging/browser/views.py
src/inqbus/tagging/browser/static/js/image_setter.js
src/inqbus/tagging/browser/templates/folder_contents.pt
src/inqbus/tagging/browser/templates/keyword_manager_view.pt
src/inqbus/tagging/browser/templates/retag.pt
src/inqbus/tagging/configuration/__init__.py
src/inqbus/tagging/configuration/utilities.py
src/inqbus/tagging/locales/README.txt
src/inqbus/tagging/locales/inqbus.tagging.pot
src/inqbus/tagging/locales/de/LC_MESSAGES/inqbus.tagging.po
src/inqbus/tagging/profiles/default/browserlayer.xml
src/inqbus/tagging/profiles/default/componentregistry.xml
src/inqbus/tagging/profiles/default/controlpanel.xml
src/inqbus/tagging/profiles/default/cssregistry.xml
src/inqbus/tagging/profiles/default/metadata.xml
src/inqbus/tagging/profiles/default/types.xml
src/inqbus/tagging/profiles/purge/componentregistry.xml
src/inqbus/tagging/profiles/remove/componentregistry.xml
src/inqbus/tagging/profiles/remove/metadata.xml
src/inqbus/tagging/profiles/remove/types.xml
src/inqbus/tagging/profiles/test_data/inqbus_tagging_test_data_marker.txt
src/inqbus/tagging/profiles/test_data/metadata.xml
src/inqbus/tagging/profiles/uninstall/metadata.xml
src/inqbus/tagging/profiles/uninstall/types.xml
src/inqbus/tagging/resources/README.txt
src/inqbus/tagging/subscriber/__init__.py
