Metadata-Version: 1.1
Name: inqbus.tagging
Version: 1.0.6
Summary: Auto tagging for Plone
Home-page: https://github.com/collective/inqbus.tagging
Author: Dr. Volker Jaenisch <volker.jaenisch@inqbus.de>, Sandra Rum <sandra.rum@inqbus.de>
Author-email: volker.jaenisch@inqbus.de
License: GPL
Keywords: Plone,tagging,keywords,autorotation,EXIF,IPTC,XMP,image,inqbus
Platform: UNKNOWN
Classifier: Framework :: Plone
Classifier: Programming Language :: Python :: 2 :: Only
Classifier: Topic :: Software Development :: Libraries :: Python Modules
Classifier: Development Status :: 3 - Alpha
Classifier: Intended Audience :: Developers
Classifier: Intended Audience :: Information Technology
Classifier: Intended Audience :: Science/Research
Classifier: Intended Audience :: Telecommunications Industry
Classifier: Topic :: Multimedia :: Graphics :: Presentation
